{
  "_format": "hh-sol-cache-2",
  "files": {
    "/home/yinka/Desktop/To-do/contracts/To-do.sol": {
      "lastModificationDate": 1661418528507,
      "contentHash": "195cf45159e64fab9668fd8ae86af637",
      "sourceName": "contracts/To-do.sol",
      "solcConfig": {
        "version": "0.8.9",
        "settings": {
          "optimizer": {
            "enabled": false,
            "runs": 200
          },
          "outputSelection": {
            "*": {
              "*": [
                "abi",
                "evm.bytecode",
                "evm.deployedBytecode",
                "evm.methodIdentifiers",
                "metadata"
              ],
              "": [
                "ast"
              ]
            }
          }
        }
      },
      "imports": [],
      "versionPragmas": [
        "^0.8.9"
      ],
      "artifacts": [
        "taskTracker"
      ]
    },
    "/home/yinka/Desktop/Lottery/contracts/lottery.sol": {
      "lastModificationDate": 1661421603220,
      "contentHash": "e5d99f97e8f832cc249913fe5cca1996",
      "sourceName": "contracts/lottery.sol",
      "solcConfig": {
        "version": "0.8.9",
        "settings": {
          "optimizer": {
            "enabled": false,
            "runs": 200
          },
          "outputSelection": {
            "*": {
              "*": [
                "abi",
                "evm.bytecode",
                "evm.deployedBytecode",
                "evm.methodIdentifiers",
                "metadata"
              ],
              "": [
                "ast"
              ]
            }
          }
        }
      },
      "imports": [],
      "versionPragmas": [
        "^0.8.9"
      ],
      "artifacts": [
        "Lotterycontract"
      ]
    }
  }
}
